{"data": {"weatherByPoint": {"forecast": {"days": [{"time": "2024-05-16T00:00:00+03:00", "parts": {"morning": {"avgTemperature": 14, "windSpeed": 3.5, "pressure": 756, "humidity": 44}, "day": {"avgTemperature": 20, "windSpeed": 3.7, "pressure": 753, "humidity": 30}, "evening": {"avgTemperature": 19, "windSpeed": 2.5, "pressure": 751, "humidity": 39}, "night": {"avgTemperature": 9, "windSpeed": 2, "pressure": 756, "humidity": 58}}}, {"time": "2024-05-17T00:00:00+03:00", "parts": {"morning": {"avgTemperature": 16, "windSpeed": 4.6, "pressure": 749, "humidity": 66}, "day": {"avgTemperature": 19, "windSpeed": 5, "pressure": 749, "humidity": 33}, "evening": {"avgTemperature": 17, "windSpeed": 4, "pressure": 750, "humidity": 35}, "night": {"avgTemperature": 15, "windSpeed": 3, "pressure": 750, "humidity": 72}}}, {"time": "2024-05-18T00:00:00+03:00", "parts": {"morning": {"avgTemperature": 13, "windSpeed": 3.7, "pressure": 753, "humidity": 46}, "day": {"avgTemperature": 18, "windSpeed": 3.5, "pressure": 752, "humidity": 28}, "evening": {"avgTemperature": 17, "windSpeed": 2.7, "pressure": 752, "humidity": 33}, "night": {"avgTemperature": 11, "windSpeed": 3, "pressure": 751, "humidity": 59}}}, {"time": "2024-05-19T00:00:00+03:00", "parts": {"morning": {"avgTemperature": 15, "windSpeed": 2.4, "pressure": 753, "humidity": 44}, "day": {"avgTemperature": 20, "windSpeed": 2.7, "pressure": 752, "humidity": 24}, "evening": {"avgTemperature": 19, "windSpeed": 2.5, "pressure": 751, "humidity": 33}, "night": {"avgTemperature": 11, "windSpeed": 1.6, "pressure": 753, "humidity": 57}}}, {"time": "2024-05-20T00:00:00+03:00", "parts": {"morning": {"avgTemperature": 15, "windSpeed": 2.7, "pressure": 752, "humidity": 56}, "day": {"avgTemperature": 23, "windSpeed": 3, "pressure": 751, "humidity": 31}, "evening": {"avgTemperature": 20, "windSpeed": 2.9, "pressure": 750, "humidity": 36}, "night": {"avgTemperature": 12, "windSpeed": 1.8, "pressure": 751, "humidity": 62}}}, {"time": "2024-05-21T00:00:00+03:00", "parts": {"morning": {"avgTemperature": 17, "windSpeed": 3, "pressure": 750, "humidity": 61}, "day": {"avgTemperature": 22, "windSpeed": 3.7, "pressure": 750, "humidity": 45}, "evening": {"avgTemperature": 20, "windSpeed": 3.4, "pressure": 750, "humidity": 48}, "night": {"avgTemperature": 15, "windSpeed": 2, "pressure": 750, "humidity": 59}}}, {"time": "2024-05-22T00:00:00+03:00", "parts": {"morning": {"avgTemperature": 15, "windSpeed": 2.7, "pressure": 751, "humidity": 67}, "day": {"avgTemperature": 19, "windSpeed": 3.7, "pressure": 751, "humidity": 53}, "evening": {"avgTemperature": 17, "windSpeed": 3.9, "pressure": 752, "humidity": 55}, "night": {"avgTemperature": 13, "windSpeed": 2.2, "pressure": 751, "humidity": 69}}}]}}}}